latch_top.py
latch_top-0.1.0.dist-info/METADATA
latch_top-0.1.0.dist-info/WHEEL
latch_top-0.1.0.dist-info/entry_points.txt
latch_top-0.1.0.dist-info/top_level.txt
latch_top-0.1.0.dist-info/RECORD
